etswatch/__init__.py
etswatch/_nbdev.py
etswatch/deployment.py
etswatch/prices.py
etswatch/eutl/__init__.py
etswatch/eutl/accounts.py
etswatch/eutl/installations.py
etswatch-0.0.1.dist-info/METADATA
etswatch-0.0.1.dist-info/WHEEL
etswatch-0.0.1.dist-info/top_level.txt
etswatch-0.0.1.dist-info/RECORD
