Metadata-Version: 2.1
Name: etswatch
Version: 0.0.1
Summary: UNKNOWN
Home-page: https://github.com/OSUKED/ETS-Watch
Author: Ayrton Bourn
Author-email: ayrtonbourn@outlook.com
License: UNKNOWN
Platform: UNKNOWN
Classifier: Programming Language :: Python :: 3
Requires-Python: >=3.6
Requires-Dist: beautifulsoup4 (==4.9.3)
Requires-Dist: feautils (==0.0.2)
Requires-Dist: html5lib (==1.1)
Requires-Dist: ipypb (==0.5.2)
Requires-Dist: lxml (==4.6.3)
Requires-Dist: matplotlib (==3.3.3)
Requires-Dist: mplfinance (==0.12.7a17)
Requires-Dist: numpy (==1.20.2)
Requires-Dist: pandas (==1.2.4)
Requires-Dist: seaborn (==0.11.0)
Requires-Dist: typer (==0.3.2)
Requires-Dist: xarray (==0.17.0)
Requires-Dist: xmltodict (==0.12.0)
